Classfile /Users/andrea/Documents/workspace/bytecodedeadlockanalysis/bin/com/laneve/test/Debug.class
  Last modified 29-mag-2015; size 390 bytes
  MD5 checksum 4ccc1de80595f50e85d36f6a1df271d3
  Compiled from "Debug.java"
public class com.laneve.test.Debug
  minor version: 0
  major version: 52
  flags: ACC_PUBLIC, ACC_SUPER
Constant pool:
   #1 = Class              #2             // com/laneve/test/Debug
   #2 = Utf8               com/laneve/test/Debug
   #3 = Class              #4             // java/lang/Object
   #4 = Utf8               java/lang/Object
   #5 = Utf8               <init>
   #6 = Utf8               ()V
   #7 = Utf8               Code
   #8 = Methodref          #3.#9          // java/lang/Object."<init>":()V
   #9 = NameAndType        #5:#6          // "<init>":()V
  #10 = Utf8               LineNumberTable
  #11 = Utf8               LocalVariableTable
  #12 = Utf8               this
  #13 = Utf8               Lcom/laneve/test/Debug;
  #14 = Utf8               main
  #15 = Utf8               ([Ljava/lang/String;)V
  #16 = Utf8               args
  #17 = Utf8               [Ljava/lang/String;
  #18 = Utf8               SourceFile
  #19 = Utf8               Debug.java
{
  public com.laneve.test.Debug();
    descriptor: ()V
    flags: ACC_PUBLIC
    Code:
      stack=1, locals=1, args_size=1
         0: aload_0
         1: invokespecial #8                  // Method java/lang/Object."<init>":()V
         4: return
      LineNumberTable:
        line 4: 0
      LocalVariableTable:
        Start  Length  Slot  Name   Signature
            0       5     0  this   Lcom/laneve/test/Debug;

  public static void main(java.lang.String[]);
    descriptor: ([Ljava/lang/String;)V
    flags: ACC_PUBLIC, ACC_STATIC
    Code:
      stack=0, locals=1, args_size=1
         0: return
      LineNumberTable:
        line 7: 0
      LocalVariableTable:
        Start  Length  Slot  Name   Signature
            0       1     0  args   [Ljava/lang/String;
}
SourceFile: "Debug.java"
