Classfile /Users/andrea/Documents/workspace/bytecodedeadlockanalysis/bin/com/laneve/test/DiningPhilosopher$Fork.class
  Last modified 29-mag-2015; size 535 bytes
  MD5 checksum 3bbbecf890180d500afc3871efc3887b
  Compiled from "DiningPhilosopher.java"
public class com.laneve.test.DiningPhilosopher$Fork
  minor version: 0
  major version: 52
  flags: ACC_PUBLIC, ACC_SUPER
Constant pool:
   #1 = Class              #2             // com/laneve/test/DiningPhilosopher$Fork
   #2 = Utf8               com/laneve/test/DiningPhilosopher$Fork
   #3 = Class              #4             // java/lang/Object
   #4 = Utf8               java/lang/Object
   #5 = Utf8               number
   #6 = Utf8               I
   #7 = Utf8               <init>
   #8 = Utf8               (I)V
   #9 = Utf8               Code
  #10 = Methodref          #3.#11         // java/lang/Object."<init>":()V
  #11 = NameAndType        #7:#12         // "<init>":()V
  #12 = Utf8               ()V
  #13 = Fieldref           #1.#14         // com/laneve/test/DiningPhilosopher$Fork.number:I
  #14 = NameAndType        #5:#6          // number:I
  #15 = Utf8               LineNumberTable
  #16 = Utf8               LocalVariableTable
  #17 = Utf8               this
  #18 = Utf8               Lcom/laneve/test/DiningPhilosopher$Fork;
  #19 = Utf8               getNumber
  #20 = Utf8               ()I
  #21 = Utf8               SourceFile
  #22 = Utf8               DiningPhilosopher.java
  #23 = Utf8               InnerClasses
  #24 = Class              #25            // com/laneve/test/DiningPhilosopher
  #25 = Utf8               com/laneve/test/DiningPhilosopher
  #26 = Utf8               Fork
{
  public com.laneve.test.DiningPhilosopher$Fork(int);
    descriptor: (I)V
    flags: ACC_PUBLIC
    Code:
      stack=2, locals=2, args_size=2
         0: aload_0
         1: invokespecial #10                 // Method java/lang/Object."<init>":()V
         4: aload_0
         5: iload_1
         6: putfield      #13                 // Field number:I
         9: return
      LineNumberTable:
        line 16: 0
        line 17: 4
        line 18: 9
      LocalVariableTable:
        Start  Length  Slot  Name   Signature
            0      10     0  this   Lcom/laneve/test/DiningPhilosopher$Fork;
            0      10     1 number   I

  public int getNumber();
    descriptor: ()I
    flags: ACC_PUBLIC
    Code:
      stack=1, locals=1, args_size=1
         0: aload_0
         1: getfield      #13                 // Field number:I
         4: ireturn
      LineNumberTable:
        line 21: 0
      LocalVariableTable:
        Start  Length  Slot  Name   Signature
            0       5     0  this   Lcom/laneve/test/DiningPhilosopher$Fork;
}
SourceFile: "DiningPhilosopher.java"
InnerClasses:
     public static #26= #1 of #24; //Fork=class com/laneve/test/DiningPhilosopher$Fork of class com/laneve/test/DiningPhilosopher
